bluerobotics_navigator-0.1.2.dist-info/METADATA
bluerobotics_navigator-0.1.2.dist-info/WHEEL
bluerobotics_navigator-0.1.2.dist-info/licenses/LICENSE
bluerobotics_navigator/__init__.py
bluerobotics_navigator/bluerobotics_navigator.abi3.so
bluerobotics_navigator-0.1.2.dist-info/RECORD
