Metadata-Version: 2.4
Name: bluerobotics_navigator
Version: 0.1.2
Classifier: Framework :: Robot Framework
Classifier: Topic :: Scientific/Engineering
Classifier: Topic :: Software Development :: Embedded Systems
Classifier: Programming Language :: Rust
License-File: LICENSE
Summary: This package serves as the entry point for embedded applications using Python on Blue Robotics's Navigator
Requires-Python: >=3.7
Project-URL: Homepage, https://bluerobotics.com/store/comm-control-power/control/navigator/
Project-URL: Documentation, https://docs.bluerobotics.com/navigator-lib/python
Project-URL: Repository, https://github.com/bluerobotics/navigator-lib
